translated_fields/__init__.py
translated_fields/admin.py
translated_fields/fields.py
translated_fields/utils.py
django_translated_fields-0.13.0.dist-info/METADATA
django_translated_fields-0.13.0.dist-info/WHEEL
django_translated_fields-0.13.0.dist-info/licenses/LICENSE
django_translated_fields-0.13.0.dist-info/RECORD
